djangoldp_scale/__init__.py
djangoldp_scale/apps.py
djangoldp_scale/models.py
djangoldp_scale/migrations/__init__.py
djangoldp_scale/templates/base.html
djangoldp_scale/templates/email.html
djangoldp_scale/templates/admin/login.html
djangoldp_scale/templates/oidc_provider/authorize.html
djangoldp_scale/templates/password/email.html
djangoldp_scale/templates/registration/login.html
djangoldp_scale/templates/registration/password_change_done.html
djangoldp_scale/templates/registration/password_reset_complete.html
djangoldp_scale/templates/registration/password_reset_confirm.html
djangoldp_scale/templates/registration/password_reset_done.html
djangoldp_scale/templates/registration/password_reset_email.html
djangoldp_scale/templates/registration/password_reset_form.html
djangoldp_scale-3.0.0.dist-info/METADATA
djangoldp_scale-3.0.0.dist-info/WHEEL
djangoldp_scale-3.0.0.dist-info/top_level.txt
djangoldp_scale-3.0.0.dist-info/RECORD
