Metadata-Version: 2.4
Name: djangoldp_scale
Version: 3.0.0
Summary: djangoldp package for BSGN-SCALE
Home-page: https://git.startinblox.com/djangoldp-packages/djangoldp-scale
Author: Startin'blox
Author-email: benoit@startinblox.com
License: MIT
Requires-Dist: djangoldp~=5.0.0
Provides-Extra: include-package-data
Requires-Dist: True; extra == "include-package-data"
